d2lib/__init__.py
d2lib/classes.py
d2lib/errors.py
d2lib/files.py
d2lib/item.py
d2lib/items_storage.py
d2lib/skills.py
d2lib/utils.py
d2lib/items_data/armor_sock_attrs.json
d2lib/items_data/armors.json
d2lib/items_data/magic_attrs.json
d2lib/items_data/magic_prefixes.json
d2lib/items_data/magic_suffixes.json
d2lib/items_data/misc.json
d2lib/items_data/quantitative.json
d2lib/items_data/rare.json
d2lib/items_data/runewords.json
d2lib/items_data/set.json
d2lib/items_data/shield_sock_attrs.json
d2lib/items_data/shields.json
d2lib/items_data/unique.json
d2lib/items_data/weapon_sock_attrs.json
d2lib/items_data/weapons.json
d2lib-0.2.4.dist-info/LICENSE
d2lib-0.2.4.dist-info/METADATA
d2lib-0.2.4.dist-info/WHEEL
d2lib-0.2.4.dist-info/top_level.txt
d2lib-0.2.4.dist-info/RECORD
