Metadata-Version: 2.1
Name: d2lib
Version: 0.2.4
Summary: Tool for retrieving information from Diablo 2 data files
Home-page: https://github.com/artcom-net/d2lib
Author: Artem Kustov
Author-email: kust.artcom@gmail.com
License: MIT
Keywords: diablo2,plugy,parser
Platform: any
Classifier: Development Status :: 4 - Beta
Classifier: Intended Audience :: Developers
Classifier: License :: OSI Approved :: MIT License
Classifier: Operating System :: OS Independent
Classifier: Programming Language :: Python
Classifier: Programming Language :: Python :: 3.6
Classifier: Programming Language :: Python :: 3.7
Classifier: Programming Language :: Python :: 3.8
Classifier: Topic :: Software Development :: Libraries :: Python Modules
Requires-Python: >= 3.6
